Workbook
Name balance_type: 1
Name calc: 1
Name co: 100
Name Codici: #REF!
Name DATOS: [3]VALRET!$C$9:$AV$120
Name FY: 2004
Name HOJA: '[4]HOJA DE DATOS'!$C$6:$R$121
Name howToChange: #REF!
Name howToChange: #REF!
Name howToChange: #REF!
Name howToCheck: #REF!
Name howToCheck: #REF!
Name howToCheck: #REF!
Name LOLD: 1
Name LOLD_Table: 120
Name NIF_DEALER: [5]Dealers!$C:$C
Name NOMBRE_DEALER: [5]Dealers!$A:$A
Name ORDINI_ATTIVI_YTD: #REF!
Name period: 12
Name round: 1
Name Stop: "Objet 33"
Name TA_2002: #REF!
Name TA_2002: #REF!
Name TA_2002: #REF!
Name TA_GLOBAL: #REF!
Name TA_GLOBAL: #REF!
Name TA_GLOBAL: #REF!
Name TABLEAUENCOURS: #REF!
Name TABLEAUENCOURS: #REF!
Name TABLEAUENCOURS: #REF!
Name value: 3
Name versionno: 1

Sheet sint HQ
B3: Company | C3: LINDE MATERIAL HANDLING VERONA S.P.A. | H3: MAIN RATIO
B4: in loc. currency/000 | C4: =+'CEE view'!C2 -> 2022 | D4: =+'CEE view'!D2 -> 2023 | E4: =+'CEE view'!E2 -> 2024 | F4: D | I4: =+C4 -> 2022 | J4: =+D4 -> 2023 | K4: =+E4 -> 2024
B5: Total sales | C5: =+'CEE view'!C84 -> 20727.579 | D5: =+'CEE view'!D84 -> 22640.669 | E5: =+'CEE view'!E84 -> 20375.419 | F5: =+IF(D5*E5<=0,"N.S",IF(AND(E5*D5>0,E5<0),-(E5-D5)/D5,(E5-D5)/D5)) -> -0.10005226 | H5: D/E | I5: =+'CEE view'!C106 -> 0.014058641 | J5: =+'CEE view'!D106 -> 0.011932601 | K5: =+'CEE view'!E106 -> -0.00015634015
B6: EBITDA | C6: =+'CEE view'!C92 -> 1605.692 | D6: =+'CEE view'!D92 -> 2385.336 | E6: =+'CEE view'!E92 -> 1907.317 | F6: =+IF(D6*E6<=0,"N.S",IF(AND(E6*D6>0,E6<0),-(E6-D6)/D6,(E6-D6)/D6)) -> -0.20039902 | H6: Equity Ratio | I6: =+'CEE view'!C108 -> 0.26234006 | J6: =+'CEE view'!D108 -> 0.25749024 | K6: =+'CEE view'!E108 -> 0.39415763
B7: Interest Expenses | C7: =-'input CEE'!B133/1000 -> -0.446 | D7: =-'input CEE'!C133/1000 -> -9.737 | E7: =-'input CEE'!D133/1000 -> -66.947 | F7: =+IF(D7*E7<=0,"N.S",IF(AND(E7*D7>0,E7<0),(E7-D7)/D7,(E7-D7)/D7)) -> 5.8755263 | H7: Current Ratio | I7: =+'CEE view'!C109 -> 4.2340938 | J7: =+'CEE view'!D109 -> 5.4439148 | K7: =+'CEE view'!E109 -> 3.6407583
B8: Net income/loss | C8: =+'CEE view'!C103 -> 558.47 | D8: =+'CEE view'!D103 -> 1012.555 | E8: =+'CEE view'!E103 -> 632.562 | F8: =+IF(D8*E8<=0,"N.S",IF(AND(E8*D8>0,E8<0),-(E8-D8)/D8,(E8-D8)/D8)) -> -0.37528134 | H8: ROS | I8: =+'CEE view'!C111 -> 0.036734391 | J8: =+'CEE view'!D111 -> 0.066272732 | K8: =+'CEE view'!E111 -> 0.046675016
B9: Operating Cash Flow | D9: =+'cash flow FGA'!D7 -> 1841.304 | E9: =+'cash flow FGA'!E7 -> 1444.136 | F9: =+IF(D9*E9<=0,"N.S",IF(AND(E9*D9>0,E9<0),-(E9-D9)/D9,(E9-D9)/D9)) -> -0.21569931 | H9: ROI | I9: =+'CEE view'!C113 -> 0.27896555 | J9: =+'CEE view'!D113 -> 0.40029981 | K9: =+'CEE view'!E113 -> 0.21933086
B10: Total assets | C10: =+'CEE view'!C5+'CEE view'!C13+'CEE view'!C18+'CEE view'!C46+'CEE view'!C64+'CEE view'!C68 -> 10259.901 | D10: =+'CEE view'!D5+'CEE view'!D13+'CEE view'!D18+'CEE view'!D46+'CEE view'!D64+'CEE view'!D68 -> 14385.547 | E10: =+'CEE view'!E5+'CEE view'!E13+'CEE view'!E18+'CEE view'!E46+'CEE view'!E64+'CEE view'!E68 -> 11002.446 | F10: =+IF(D10*E10<=0,"N.S",IF(AND(E10*D10>0,E10<0),-(E10-D10)/D10,(E10-D10)/D10)) -> -0.23517361 | H10: ROE | I10: =+'CEE view'!C114 -> 0.20748756 | J10: =+'CEE view'!D114 -> 0.2733578 | K10: =+'CEE view'!E114 -> 0.14586259
B11: Inventory | C11: =+'CEE view'!C13 -> 1943.708 | D11: =+'CEE view'!D13 -> 4786.515 | E11: =+'CEE view'!E13 -> 2217.839 | F11: =+IF(D11*E11<=0,"N.S",IF(AND(E11*D11>0,E11<0),-(E11-D11)/D11,(E11-D11)/D11)) -> -0.53664848
B12: Financial Debt | C12: =-(+'CEE view'!C72) -> 41.257 | D12: =-(+'CEE view'!D72) -> 45.235 | E12: =-(+'CEE view'!E72) -> 0 | F12: =+IF(D12*E12<=0,"N.S",IF(AND(E12*D12>0,E12<0),(E12-D12)/D12,(E12-D12)/D12)) -> N.S
B13: o/w short term debt | C13: =-(+'CEE view'!C73+'CEE view'!C75+'CEE view'!C77+'CEE view'!C78) -> 41.257 | D13: =-(+'CEE view'!D73+'CEE view'!D75+'CEE view'!D77+'CEE view'!D78) -> 45.235 | E13: =-(+'CEE view'!E73+'CEE view'!E75+'CEE view'!E77+'CEE view'!E78) -> 0 | F13: =+IF(D13*E13<=0,"N.S",IF(AND(E13*D13>0,E13<0),(E13-D13)/D13,(E13-D13)/D13)) -> N.S
B14: o/w m/l term debt | C14: =-(+'CEE view'!C76+'CEE view'!C74) -> 0 | D14: =-(+'CEE view'!D76+'CEE view'!D74) -> 0 | E14: =-(+'CEE view'!E76+'CEE view'!E74) -> 0 | F14: =+IF(D14*E14<=0,"N.S",IF(AND(E14*D14>0,E14<0),(E14-D14)/D14,(E14-D14)/D14)) -> N.S
B15: Net Worth | C15: =+'CEE view'!C63 -> 2691.583 | D15: =+'CEE view'!D63 -> 3704.138 | E15: =+'CEE view'!E63 -> 4336.698 | F15: =+IF(D15*E15<=0,"N.S",IF(AND(E15*D15>0,E15<0),-(E15-D15)/D15,(E15-D15)/D15)) -> 0.17077118
B16: Day receivables | C16: =+'CEE view'!C116 -> 84.47302 | D16: =+'CEE view'!D116 -> 60.539557 | E16: =+'CEE view'!E116 -> 67.295223 | F16: =+E16-D16 -> 6.7556654

Sheet cash flow FGA
B2: €/000 | D2: =+'CEE view'!D2 -> 2023 | E2: =+'CEE view'!E2 -> 2024
B4: net result | D4: =+'CEE view'!D103 -> 1012.555 | E4: =+'CEE view'!E103 -> 632.562 | G4: risultato netto | H4: net result
B5: depreciation | D5: =-('CEE view'!D94+'CEE view'!D95) -> 689.085 | E5: =-('CEE view'!E94+'CEE view'!E95) -> 768.733 | G5: dedotte le quote di ammortamento | H5: deducted the depreciation charges
B6: provisions | D6: =('CEE view'!C47-'CEE view'!D47)+('CEE view'!C28-'CEE view'!D28) -> 139.664 | E6: =('CEE view'!D47-'CEE view'!E47)+('CEE view'!D28-'CEE view'!E28) -> 42.841 | G6: a dedurre incrementi (o rilasci se con segno negativo) di fondi rischi e di fondi svalutazione crediti o trattamento di fine rapporto | H6: deducing increase (or decrease in case of negative sign) of risks provisions, bad debts provisions or severance pay (long-term provisions)
B7: OPERATING CASH FLOW | C7: (a) | D7: =SUM(D4:D6) -> 1841.304 | E7: =SUM(E4:E6) -> 1444.136 | G7: totale flusso di cassa dalle attività operative | H7: operating cash flow
B9: (increase)/decrease receivables | D9: =('CEE view'!C6+'CEE view'!C7+'CEE view'!C8+'CEE view'!C9+'CEE view'!C10+'CEE view'!C11+'CEE view'!C12+'CEE view'!C18)-('CEE view'!D6+'CEE view'!D7+'CEE view'!D8+'CEE view'!D9+'CEE view'!D10+'CEE view'!D11+'CEE view'!D12+'CEE view'!D18) -> -1006.257 | E9: =('CEE view'!D6+'CEE view'!D7+'CEE view'!D8+'CEE view'!D9+'CEE view'!D10+'CEE view'!D11+'CEE view'!D12+'CEE view'!D18)-('CEE view'!E6+'CEE view'!E7+'CEE view'!E8+'CEE view'!E9+'CEE view'!E10+'CEE view'!E11+'CEE view'!E12+'CEE view'!E18) -> 1385.296 | G9: incremento (con segno negativo) o decremento (con segno positivo) di crediti commerciali | H9: increase (in case of negative sign) or decrease (in case of positive sign) in trade receivables
B10: (increase)/decrease stock | D10: =('CEE view'!C13-'CEE view'!D13) -> -2842.807 | E10: =('CEE view'!D13-'CEE view'!E13) -> 2568.676 | G10: incremento (con segno negativo) o decremento (con segno positivo) di magazzino | H10: increase (in case of negative sign) or decrease (in case of positive sign) in stock
B11: increase/(decrease) payables | D11: =('CEE view'!C19-'CEE view'!D19)+('CEE view'!C27-'CEE view'!D27) -> 2969.449 | E11: =('CEE view'!D19-'CEE view'!E19)+('CEE view'!D27-'CEE view'!E27) -> -4013.267 | G11: incremento (con segno positivo) o decremento (con segno negativo) di debiti commerciali | H11: increase (in case of positive sign) or decrease (in case of negative sign) in trade payables
B12: working capital variation | D12: =SUM(D9:D11) -> -879.615 | E12: =SUM(E9:E11) -> -59.295 | G12: variazione di capitale circolante | H12: working capital variation
B14: (increase)/decrease fixed assets | D14: =('CEE view'!C30-'CEE view'!D30+'CEE view'!D95)+('CEE view'!C36-'CEE view'!D36+'CEE view'!D94)+('CEE view'!C42-'CEE view'!D42) -> -968.049 | E14: =('CEE view'!D30-'CEE view'!E30+'CEE view'!E95)+('CEE view'!D36-'CEE view'!E36+'CEE view'!E94)+('CEE view'!D42-'CEE view'!E42) -> -1339.961 | G14: incremento (con segno negativo) o decremento (con segno positivo) di investimenti al netto della quota di ammortamento | H14: increase (in case of negative sign) or decrease (in case of positive sign) in fixed assets, net of depreciation charge
B15: increase/(decrease) equity or reserve | D15: =('CEE view'!D53-'CEE view'!C53-'CEE view'!C62)+('CEE view'!D49-'CEE view'!C49)+('CEE view'!D61-'CEE view'!C61)+('CEE view'!D60-'CEE view'!C60) -> 0 | E15: =('CEE view'!E53-'CEE view'!D53-'CEE view'!D62)+('CEE view'!E49-'CEE view'!D49)+('CEE view'!E61-'CEE view'!D61)+('CEE view'!E60-'CEE view'!D60) -> -0.002 | G15: versamenti (con segno positivo) o prelievi (con segno negativo) di capitale sociale o di riserve in patrimonio netto | H15: cash-in (in case of positive sign) or cash-out (in case of negative sign) of share capital or reserves in the shareholders' equity
B16: extra operating activities | D16: =SUM(D14:D15) -> -968.049 | E16: =SUM(E14:E15) -> -1339.963 | G16: flusso di cassa dalle attività extra-operative | H16: extra operating activities
B18: EXTRA OPERATING CASH FLOW | C18: (b) | D18: =+D12+D16 -> -1847.664 | E18: =+E12+E16 -> -1399.258 | G18: totale flusso di cassa dalle attività extra-operative | H18: extra operating cash flow
B20: (INCREASE)/DECREASE IN FINANCIAL NEEDS | C20: (a+b) | D20: =+D18+D7 -> -6.36 | E20: =+E18+E7 -> 44.878 | G20: incremento (con segno negativo) o decremento (con segno positivo) del fabbisogno finanziario | H20: increase (in case of negative sign) or decrease (in case of positive sign) in financial needs
B22: (increase)/decrease financial debts | D22: =('CEE view'!D73+'CEE view'!D75+'CEE view'!D77+'CEE view'!D78)-('CEE view'!C73+'CEE view'!C75+'CEE view'!C77+'CEE view'!C78) -> -3.978 | E22: =('CEE view'!E73+'CEE view'!E75+'CEE view'!E77+'CEE view'!E78)-('CEE view'!D73+'CEE view'!D75+'CEE view'!D77+'CEE view'!D78) -> 45.235 | G22: incremento (con segno negativo) o decremento (con segno positivo) di debiti finanziari a breve termine | H22: increase (in case of negative sign) or decrease (in case of positive sign) of short term financial debts
B23: increase/(decrease) financial receivables (or cash) | D23: =('CEE view'!D64+'CEE view'!D68)-('CEE view'!C64+'CEE view'!C68) -> -2.382 | E23: =('CEE view'!E64+'CEE view'!E68)-('CEE view'!D64+'CEE view'!D68) -> -0.357 | G23: incremento (con segno positivo) o decremento (con segno negativo) di crediti finanziari o liquidità (cassa) | H23: increase (in case of positive sign) or decrease (in case of negative sign) of financial receivables or cash
B24: short-term debts variation | C24: (d) | D24: =SUM(D22:D23) -> -6.36 | E24: =SUM(E22:E23) -> 44.878 | G24: variazione dell'indebitamento a breve | H24: increase (in case of negative sign) or decrease (in case of positive sign) of short-term debts
B26: (increase)/decrease medium/long-term debts | C26: (e) | D26: =('CEE view'!D74+'CEE view'!D76)-('CEE view'!C74+'CEE view'!C76) -> 0 | E26: =('CEE view'!E74+'CEE view'!E76)-('CEE view'!D74+'CEE view'!D76) -> 0 | G26: variazione dell'indebitamento a medio/lungo | H26: increase (in case of negative sign) or decrease (in case of positive sign) of medium long-term debts
B27: of which new loans
B28: of which installments paid
B30: VARIATION FINANCIAL POSITION | C30: (d+e) | D30: =+D24+D26 -> -6.36 | E30: =+E24+E26 -> 44.878 | G30: variazione della posizione finanziaria | H30: financial position's variation
D32: =+D30-D20 -> -6.2403416e-12 | E32: =+E30-E20 -> -3.7942982e-12

Sheet CEE view
C2: =+'input CEE'!B1 -> 2022 | D2: =+'input CEE'!C1 -> 2023 | E2: =+'input CEE'!D1 -> 2024 | G2: ê | K2: CASH FLOW (dettaglio)
G3: valore | H3: %
A4: BALANCE SHEET
A5: 1) COMMERCIAL RECEIVABLES | C5: =SUM(C6:C12) -> 6523.065 | D5: =SUM(D6:D12) -> 7534.153 | E5: =SUM(E6:E12) -> 6144.911 | G5: =+E5-D5 -> -1389.242 | H5: =+IF(D5*E5<=0,"N.S",IF(AND(D5*E5>0,E5<0),-(E5-D5)/D5,(E5-D5)/D5)) -> -0.18439259 | K5: =-G18-G5 -> 1385.296 | L5: =+'cash flow FGA'!B9 -> (increase)/decrease receivables
A6: Trade receivables min 12 months | C6: =+'input CEE'!B47/1000 -> 4863.67 | D6: =+'input CEE'!C47/1000 -> 3807.378 | E6: =+'input CEE'!D47/1000 -> 3808.801 | G6: =+E6-D6 -> 1.423 | H6: =+IF(D6*E6<=0,"N.S",IF(AND(D6*E6>0,E6<0),-(E6-D6)/D6,(E6-D6)/D6)) -> 0.00037374802
A7: Trade receivables >12 months | C7: =+'input CEE'!B48/1000 -> 0 | D7: =+'input CEE'!C48/1000 -> 0 | E7: =+'input CEE'!D48/1000 -> 0 | G7: =+E7-D7 -> 0 | H7: =+IF(D7*E7<=0,"N.S",IF(AND(D7*E7>0,E7<0),-(E7-D7)/D7,(E7-D7)/D7)) -> N.S
A8: Receivables towards related companies | C8: =('input CEE'!B49+'input CEE'!B55)/1000 -> 1327.663 | D8: =('input CEE'!C49+'input CEE'!C55)/1000 -> 2858.485 | E8: =('input CEE'!D49+'input CEE'!D55)/1000 -> 1996.009 | G8: =+E8-D8 -> -862.476 | H8: =+IF(D8*E8<=0,"N.S",IF(AND(D8*E8>0,E8<0),-(E8-D8)/D8,(E8-D8)/D8)) -> -0.30172486
A9: Other receivables min 12 months | C9: =+'input CEE'!B63/1000 -> 7.545 | D9: =+'input CEE'!C63/1000 -> 12.594 | E9: =+'input CEE'!D63/1000 -> 33.053 | G9: =+E9-D9 -> 20.459 | H9: =+IF(D9*E9<=0,"N.S",IF(AND(D9*E9>0,E9<0),-(E9-D9)/D9,(E9-D9)/D9)) -> 1.6245037
A10: Other receivables >12 months | C10: =+'input CEE'!B64/1000 -> 0 | D10: =+'input CEE'!C64/1000 -> 0 | E10: =+'input CEE'!D64/1000 -> 0 | G10: =+E10-D10 -> 0 | H10: =+IF(D10*E10<=0,"N.S",IF(AND(D10*E10>0,E10<0),-(E10-D10)/D10,(E10-D10)/D10)) -> N.S
A11: VAT and TAX receivables -Current | C11: =('input CEE'!B57+'input CEE'!B60)/1000 -> 324.187 | D11: =('input CEE'!C57+'input CEE'!C60)/1000 -> 855.696 | E11: =('input CEE'!D57+'input CEE'!D60)/1000 -> 307.048 | G11: =+E11-D11 -> -548.648 | H11: =+IF(D11*E11<=0,"N.S",IF(AND(D11*E11>0,E11<0),-(E11-D11)/D11,(E11-D11)/D11)) -> -0.64117163
A12: VAT and TAX receivables - Deferred | C12: =('input CEE'!B58+'input CEE'!B61)/1000 -> 0 | D12: =('input CEE'!C58+'input CEE'!C61)/1000 -> 0 | E12: =('input CEE'!D58+'input CEE'!D61)/1000 -> 0 | G12: =+E12-D12 -> 0 | H12: =+IF(D12*E12<=0,"N.S",IF(AND(D12*E12>0,E12<0),-(E12-D12)/D12,(E12-D12)/D12)) -> N.S
A13: 2) STOCK | C13: =SUM(C14:C17) -> 1943.708 | D13: =SUM(D14:D17) -> 4786.515 | E13: =SUM(E14:E17) -> 2217.839 | G13: =+E13-D13 -> -2568.676 | H13: =+IF(D13*E13<=0,"N.S",IF(AND(D13*E13>0,E13<0),-(E13-D13)/D13,(E13-D13)/D13)) -> -0.53664848 | K13: =-G13 -> 2568.676 | L13: =+'cash flow FGA'!B10 -> (increase)/decrease stock
A14: Raw materials and consumables | C14: =+'input CEE'!B40/1000 -> 1943.708 | D14: =+'input CEE'!C40/1000 -> 4786.515 | E14: =+'input CEE'!D40/1000 -> 2217.839 | G14: =+E14-D14 -> -2568.676 | H14: =+IF(D14*E14<=0,"N.S",IF(AND(D14*E14>0,E14<0),-(E14-D14)/D14,(E14-D14)/D14)) -> -0.53664848
A15: Work in progress | C15: =+'input CEE'!B41/1000 -> 0 | D15: =+'input CEE'!C41/1000 -> 0 | E15: =+'input CEE'!D41/1000 -> 0 | G15: =+E15-D15 -> 0 | H15: =+IF(D15*E15<=0,"N.S",IF(AND(D15*E15>0,E15<0),-(E15-D15)/D15,(E15-D15)/D15)) -> N.S
A16: Contract work-in-progress | C16: =('input CEE'!B42+'input CEE'!B44)/1000 -> 0 | D16: =('input CEE'!C42+'input CEE'!C44)/1000 -> 0 | E16: =('input CEE'!D42+'input CEE'!D44)/1000 -> 0 | G16: =+E16-D16 -> 0 | H16: =+IF(D16*E16<=0,"N.S",IF(AND(D16*E16>0,E16<0),-(E16-D16)/D16,(E16-D16)/D16)) -> N.S
A17: Finished goods and goods for resale | C17: =+'input CEE'!B43/1000 -> 0 | D17: =+'input CEE'!C43/1000 -> 0 | E17: =+'input CEE'!D43/1000 -> 0 | G17: =+E17-D17 -> 0 | H17: =+IF(D17*E17<=0,"N.S",IF(AND(D17*E17>0,E17<0),-(E17-D17)/D17,(E17-D17)/D17)) -> N.S
A18: 3) POSITIVE PREPAYMENTS AND ACCRUALS | C18: =+'input CEE'!B79/1000 -> 28.021 | D18: =+'input CEE'!C79/1000 -> 23.19 | E18: =+'input CEE'!D79/1000 -> 27.136 | G18: =+E18-D18 -> 3.946 | H18: =+IF(D18*E18<=0,"N.S",IF(AND(D18*E18>0,E18<0),-(E18-D18)/D18,(E18-D18)/D18)) -> 0.17015955
A19: 4) (COMMERCIAL PAYABLES) | C19: =SUM(C20:C26) -> -7450.445 | D19: =SUM(D20:D26) -> -10448.799 | E19: =SUM(E20:E26) -> -6457.238 | G19: =+E19-D19 -> 3991.561 | H19: =+IF(D19*E19<=0,"N.S",IF(AND(D19*E19>0,E19<0),-(E19-D19)/D19,(E19-D19)/D19)) -> 0.38201146 | K19: =-G27-G19 -> -4013.267 | L19: =+'cash flow FGA'!B11 -> increase/(decrease) payables
A20: Suppliers, trade payables min 12 months | C20: =-'input CEE'!G52/1000 -> -947.195 | D20: =-'input CEE'!H52/1000 -> -1032.244 | E20: =-'input CEE'!I52/1000 -> -972.098 | G20: =+E20-D20 -> 60.146 | H20: =+IF(D20*E20<=0,"N.S",IF(AND(D20*E20>0,E20<0),-(E20-D20)/D20,(E20-D20)/D20)) -> 0.058267231
A21: Suppliers, trade payables >12 months | C21: =-'input CEE'!G53/1000 -> 0 | D21: =-'input CEE'!H53/1000 -> 0 | E21: =-'input CEE'!I53/1000 -> 0 | G21: =+E21-D21 -> 0 | H21: =+IF(D21*E21<=0,"N.S",IF(AND(D21*E21>0,E21<0),-(E21-D21)/D21,(E21-D21)/D21)) -> N.S
A22: Payables towards related company | C22: =-'input CEE'!G57/1000 -> -4193.285 | D22: =-'input CEE'!H57/1000 -> -8306.699 | E22: =-'input CEE'!I57/1000 -> -4233.159 | G22: =+E22-D22 -> 4073.54 | H22: =+IF(D22*E22<=0,"N.S",IF(AND(D22*E22>0,E22<0),-(E22-D22)/D22,(E22-D22)/D22)) -> 0.49039215
A23: Advances by customers | C23: =-'input CEE'!G48/1000 -> -1676.35 | D23: =-'input CEE'!H48/1000 -> -487.318 | E23: =-'input CEE'!I48/1000 -> -488.547 | G23: =+E23-D23 -> -1.229 | H23: =+IF(D23*E23<=0,"N.S",IF(AND(D23*E23>0,E23<0),-(E23-D23)/D23,(E23-D23)/D23)) -> -0.0025219672
A24: Other debts | C24: =-('input CEE'!G66+'input CEE'!G69)/1000 -> -542.429 | D24: =-('input CEE'!H66+'input CEE'!H69)/1000 -> -527.57 | E24: =-('input CEE'!I66+'input CEE'!I69)/1000 -> -499.939 | G24: =+E24-D24 -> 27.631 | H24: =+IF(D24*E24<=0,"N.S",IF(AND(D24*E24>0,E24<0),-(E24-D24)/D24,(E24-D24)/D24)) -> 0.052374093
A25: VAT and Tax payables - Current | C25: =-('input CEE'!G64)/1000 -> -91.186 | D25: =-('input CEE'!H64)/1000 -> -94.968 | E25: =-('input CEE'!I64)/1000 -> -263.495 | G25: =+E25-D25 -> -168.527 | H25: =+IF(D25*E25<=0,"N.S",IF(AND(D25*E25>0,E25<0),-(E25-D25)/D25,(E25-D25)/D25)) -> -1.7745662
A26: VAT and TAX payables - Deferred | C26: =-('input CEE'!G65)/1000 -> 0 | D26: =-('input CEE'!H65)/1000 -> 0 | E26: =-('input CEE'!I65)/1000 -> 0 | G26: =+E26-D26 -> 0 | H26: =+IF(D26*E26<=0,"N.S",IF(AND(D26*E26>0,E26<0),-(E26-D26)/D26,(E26-D26)/D26)) -> N.S
A27: 5) (NEGATIVE PREPAYMENTS AND ACCRUALS) | C27: =-'input CEE'!G74/1000 -> -71.459 | D27: =-'input CEE'!H74/1000 -> -42.554 | E27: =-'input CEE'!I74/1000 -> -20.848 | G27: =+E27-D27 -> 21.706 | H27: =+IF(D27*E27<=0,"N.S",IF(AND(D27*E27>0,E27<0),-(E27-D27)/D27,(E27-D27)/D27)) -> 0.51008131
A28: 6) (OTHER PROVISIONS - SHORT TERM) | C28: =-'input CEE'!G26/1000 -> -5.157 | D28: =-'input CEE'!H26/1000 -> -144.821 | E28: =-'input CEE'!I26/1000 -> -187.662 | G28: =+E28-D28 -> -42.841 | H28: =+IF(D28*E28<=0,"N.S",IF(AND(D28*E28>0,E28<0),-(E28-D28)/D28,(E28-D28)/D28)) -> -0.29582036 | K28: =-G47-G28 -> 42.841 | L28: =+'cash flow FGA'!B6 -> provisions
A29: A) NET WORKING CAPITAL (1+2+3+4+5+6) | C29: =+C5+C13+C18+C19+C27+C28 -> 967.733 | D29: =+D5+D13+D18+D19+D27+D28 -> 1707.684 | E29: =+E5+E13+E18+E19+E27+E28 -> 1724.138 | G29: =+E29-D29 -> 16.454 | H29: =+IF(D29*E29<=0,"N.S",IF(AND(D29*E29>0,E29<0),-(E29-D29)/D29,(E29-D29)/D29)) -> 0.0096352721
A30: 7) NET INTANGIBLE FIXED ASSETS | C30: =SUM(C31:C35) -> 12.301 | D30: =SUM(D31:D35) -> 6.565 | E30: =SUM(E31:E35) -> 0.48 | G30: =+E30-D30 -> -6.085 | H30: =+IF(D30*E30<=0,"N.S",IF(AND(D30*E30>0,E30<0),-(E30-D30)/D30,(E30-D30)/D30)) -> -0.926885
A31: Estabilishment costs | C31: =+'input CEE'!B9/1000 -> 0 | D31: =+'input CEE'!C9/1000 -> 0 | E31: =+'input CEE'!D9/1000 -> 0 | G31: =+E31-D31 -> 0 | H31: =+IF(D31*E31<=0,"N.S",IF(AND(D31*E31>0,E31<0),-(E31-D31)/D31,(E31-D31)/D31)) -> N.S
A32: Development costs | C32: =+'input CEE'!B10/1000 -> 0 | D32: =+'input CEE'!C10/1000 -> 0 | E32: =+'input CEE'!D10/1000 -> 0 | G32: =+E32-D32 -> 0 | H32: =+IF(D32*E32<=0,"N.S",IF(AND(D32*E32>0,E32<0),-(E32-D32)/D32,(E32-D32)/D32)) -> N.S
A33: Royalties | C33: =+'input CEE'!B11/1000 -> 0 | D33: =+'input CEE'!C11/1000 -> 0 | E33: =+'input CEE'!D11/1000 -> 0 | G33: =+E33-D33 -> 0 | H33: =+IF(D33*E33<=0,"N.S",IF(AND(D33*E33>0,E33<0),-(E33-D33)/D33,(E33-D33)/D33)) -> N.S
A34: Goodwill | C34: =+'input CEE'!B13/1000 -> 0 | D34: =+'input CEE'!C13/1000 -> 0 | E34: =+'input CEE'!D13/1000 -> 0 | G34: =+E34-D34 -> 0 | H34: =+IF(D34*E34<=0,"N.S",IF(AND(D34*E34>0,E34<0),-(E34-D34)/D34,(E34-D34)/D34)) -> N.S
A35: Other intangible assets (specify) | C35: =('input CEE'!B12+'input CEE'!B14+'input CEE'!B15)/1000 -> 12.301 | D35: =('input CEE'!C12+'input CEE'!C14+'input CEE'!C15)/1000 -> 6.565 | E35: =('input CEE'!D12+'input CEE'!D14+'input CEE'!D15)/1000 -> 0.48 | G35: =+E35-D35 -> -6.085 | H35: =+IF(D35*E35<=0,"N.S",IF(AND(D35*E35>0,E35<0),-(E35-D35)/D35,(E35-D35)/D35)) -> -0.926885
A36: 8) NET TANGIBLE FIXED ASSETS | C36: =SUM(C37:C41) -> 1708.439 | D36: =SUM(D37:D41) -> 1993.139 | E36: =SUM(E37:E41) -> 2551.402 | G36: =+E36-D36 -> 558.263 | H36: =+IF(D36*E36<=0,"N.S",IF(AND(D36*E36>0,E36<0),-(E36-D36)/D36,(E36-D36)/D36)) -> 0.28009236
A37: Land and buildings - Freehold | C37: =+'input CEE'!B17/1000 -> 0 | D37: =+'input CEE'!C17/1000 -> 0 | E37: =+'input CEE'!D17/1000 -> 0 | G37: =+E37-D37 -> 0 | H37: =+IF(D37*E37<=0,"N.S",IF(AND(D37*E37>0,E37<0),-(E37-D37)/D37,(E37-D37)/D37)) -> N.S
A38: Machinery | C38: =+'input CEE'!B18/1000 -> 0 | D38: =+'input CEE'!C18/1000 -> 0 | E38: =+'input CEE'!D18/1000 -> 0 | G38: =+E38-D38 -> 0 | H38: =+IF(D38*E38<=0,"N.S",IF(AND(D38*E38>0,E38<0),-(E38-D38)/D38,(E38-D38)/D38)) -> N.S
A39: Equipments | C39: =+'input CEE'!B19/1000 -> 15.477 | D39: =+'input CEE'!C19/1000 -> 19.754 | E39: =+'input CEE'!D19/1000 -> 7.307 | G39: =+E39-D39 -> -12.447 | H39: =+IF(D39*E39<=0,"N.S",IF(AND(D39*E39>0,E39<0),-(E39-D39)/D39,(E39-D39)/D39)) -> -0.63010023
A40: Advances for capital project | C40: =+'input CEE'!B21/1000 -> 0 | D40: =+'input CEE'!C21/1000 -> 0 | E40: =+'input CEE'!D21/1000 -> 0 | G40: =+E40-D40 -> 0 | H40: =+IF(D40*E40<=0,"N.S",IF(AND(D40*E40>0,E40<0),-(E40-D40)/D40,(E40-D40)/D40)) -> N.S
A41: Other tangible assets (specify) | C41: =+'input CEE'!B20/1000 -> 1692.962 | D41: =+'input CEE'!C20/1000 -> 1973.385 | E41: =+'input CEE'!D20/1000 -> 2544.095 | G41: =+E41-D41 -> 570.71 | H41: =+IF(D41*E41<=0,"N.S",IF(AND(D41*E41>0,E41<0),-(E41-D41)/D41,(E41-D41)/D41)) -> 0.28920358
A42: 9) NET FINANCIAL FIXED ASSETS | C42: =SUM(C43:C45) -> 40.95 | D42: =SUM(D43:D45) -> 40.95 | E42: =SUM(E43:E45) -> 60 | G42: =+E42-D42 -> 19.05 | H42: =+IF(D42*E42<=0,"N.S",IF(AND(D42*E42>0,E42<0),-(E42-D42)/D42,(E42-D42)/D42)) -> 0.46520147
A43: Shares | C43: ='input CEE'!B23/1000 -> 0 | D43: ='input CEE'!C23/1000 -> 40.95 | E43: ='input CEE'!D23/1000 -> 0 | G43: =+E43-D43 -> -40.95 | H43: =+IF(D43*E43<=0,"N.S",IF(AND(D43*E43>0,E43<0),-(E43-D43)/D43,(E43-D43)/D43)) -> N.S
A44: Credits | C44: =('input CEE'!B29 +'input CEE'!B3)/1000 -> 40.95 | D44: =('input CEE'!C29 +'input CEE'!C3)/1000 -> 0 | E44: =('input CEE'!D29 +'input CEE'!D3)/1000 -> 60 | G44: =+E44-D44 -> 60 | H44: =+IF(D44*E44<=0,"N.S",IF(AND(D44*E44>0,E44<0),-(E44-D44)/D44,(E44-D44)/D44)) -> N.S
A45: Other financial assets (specify) | C45: =('input CEE'!B35+'input CEE'!B36)/1000 -> 0 | D45: =('input CEE'!C35+'input CEE'!C36)/1000 -> 0 | E45: =('input CEE'!D35+'input CEE'!D36)/1000 -> 0 | G45: =+E45-D45 -> 0 | H45: =+IF(D45*E45<=0,"N.S",IF(AND(D45*E45>0,E45<0),-(E45-D45)/D45,(E45-D45)/D45)) -> N.S
A46: B) TOTAL NET FIXED ASSETS (7+8+9) | C46: =+C30+C36+C42 -> 1761.69 | D46: =+D30+D36+D42 -> 2040.654 | E46: =+E30+E36+E42 -> 2611.882 | G46: =+E46-D46 -> 571.228 | H46: =+IF(D46*E46<=0,"N.S",IF(AND(D46*E46>0,E46<0),-(E46-D46)/D46,(E46-D46)/D46)) -> 0.27992399 | K46: =-G46+E94+E95 -> -1339.961 | L46: =+'cash flow FGA'!B14 -> (increase)/decrease fixed assets
A47: 10) (OTHER PROVISIONS - LONG TERM) | C47: =-'input CEE'!G32/1000 -> 0 | D47: =-'input CEE'!H32/1000 -> 0 | E47: =-'input CEE'!I32/1000 -> 0 | G47: =+E47-D47 -> 0 | H47: =+IF(D47*E47<=0,"N.S",IF(AND(D47*E47>0,E47<0),-(E47-D47)/D47,(E47-D47)/D47)) -> N.S
A48: C) NET INVESTED CAPITAL (A+B+10) | C48: =+C29+C46+C47 -> 2729.423 | D48: =+D29+D46+D47 -> 3748.338 | E48: =+E29+E46+E47 -> 4336.02 | G48: =+E48-D48 -> 587.682 | H48: =+IF(D48*E48<=0,"N.S",IF(AND(D48*E48>0,E48<0),-(E48-D48)/D48,(E48-D48)/D48)) -> 0.15678469
A49: 11) EQUITY CAPITAL | C49: =SUM(C50:C52) -> 1000 | D49: =SUM(D50:D52) -> 1000 | E49: =SUM(E50:E52) -> 1000 | G49: =+E49-D49 -> 0 | H49: =+IF(D49*E49<=0,"N.S",IF(AND(D49*E49>0,E49<0),-(E49-D49)/D49,(E49-D49)/D49)) -> 0
A50: Official Equity - ordinary shares | C50: =+'input CEE'!G5/1000 -> 1000 | D50: =+'input CEE'!H5/1000 -> 1000 | E50: =+'input CEE'!I5/1000 -> 1000 | G50: =+E50-D50 -> 0 | H50: =+IF(D50*E50<=0,"N.S",IF(AND(D50*E50>0,E50<0),-(E50-D50)/D50,(E50-D50)/D50)) -> 0
A51: Subordinated loan | C51: =+'input CEE'!G12/1000 -> 0 | D51: =+'input CEE'!H12/1000 -> 0 | E51: =+'input CEE'!I12/1000 -> 0 | G51: =+E51-D51 -> 0 | H51: =+IF(D51*E51<=0,"N.S",IF(AND(D51*E51>0,E51<0),-(E51-D51)/D51,(E51-D51)/D51)) -> N.S
A52: Minority Interest | C52: ='input CEE'!G23/1000 -> 0 | D52: ='input CEE'!H23/1000 -> 0 | E52: ='input CEE'!I23/1000 -> 0 | G52: =+E52-D52 -> 0 | H52: =+IF(D52*E52<=0,"N.S",IF(AND(D52*E52>0,E52<0),-(E52-D52)/D52,(E52-D52)/D52)) -> N.S
A53: 12) RESERVES | C53: =SUM(C54:C59) -> 94.074 | D53: =SUM(D54:D59) -> 121.997 | E53: =SUM(E54:E59) -> 172.623 | G53: =+E53-D53 -> 50.626 | H53: =+IF(D53*E53<=0,"N.S",IF(AND(D53*E53>0,E53<0),-(E53-D53)/D53,(E53-D53)/D53)) -> 0.41497742
A54: Legal | C54: =+'input CEE'!G8/1000 -> 94.072 | D54: =+'input CEE'!H8/1000 -> 121.994 | E54: =+'input CEE'!I8/1000 -> 172.623 | G54: =+E54-D54 -> 50.629 | H54: =+IF(D54*E54<=0,"N.S",IF(AND(D54*E54>0,E54<0),-(E54-D54)/D54,(E54-D54)/D54)) -> 0.41501221
A55: Revaluation | C55: =+'input CEE'!G7/1000 -> 0 | D55: =+'input CEE'!H7/1000 -> 0 | E55: =+'input CEE'!I7/1000 -> 0 | G55: =+E55-D55 -> 0 | H55: =+IF(D55*E55<=0,"N.S",IF(AND(D55*E55>0,E55<0),-(E55-D55)/D55,(E55-D55)/D55)) -> N.S
A56: Share premium | C56: =+'input CEE'!G6/1000 -> 0 | D56: =+'input CEE'!H6/1000 -> 0 | E56: =+'input CEE'!I6/1000 -> 0 | G56: =+E56-D56 -> 0 | H56: =+IF(D56*E56<=0,"N.S",IF(AND(D56*E56>0,E56<0),-(E56-D56)/D56,(E56-D56)/D56)) -> N.S
A57: Other reserves | C57: =('input CEE'!G9+'input CEE'!G11+'input CEE'!G13+'input CEE'!G14+'input CEE'!G15+'input CEE'!G16+'input CEE'!G17)/1000 -> 0.002 | D57: =('input CEE'!H9+'input CEE'!H11+'input CEE'!H13+'input CEE'!H14+'input CEE'!H15+'input CEE'!H16+'input CEE'!H17)/1000 -> 0.003 | E57: =('input CEE'!I9+'input CEE'!I11+'input CEE'!I13+'input CEE'!I14+'input CEE'!I15+'input CEE'!I16+'input CEE'!I17)/1000 -> 0 | G57: =+E57-D57 -> -0.003 | H57: =+IF(D57*E57<=0,"N.S",IF(AND(D57*E57>0,E57<0),-(E57-D57)/D57,(E57-D57)/D57)) -> N.S
A58: Hedging reserve for future expected cash flows | C58: ='input CEE'!G18/1000 -> 0 | D58: ='input CEE'!H18/1000 -> 0 | E58: ='input CEE'!I18/1000 -> 0 | G58: =+E58-D58 -> 0 | H58: =+IF(D58*E58<=0,"N.S",IF(AND(D58*E58>0,E58<0),-(E58-D58)/D58,(E58-D58)/D58)) -> N.S
A59: Negative reserve for own shares | C59: ='input CEE'!G21/1000 -> 0 | D59: ='input CEE'!H21/1000 -> 0 | E59: ='input CEE'!I21/1000 -> 0 | G59: =+E59-D59 -> 0 | H59: =+IF(D59*E59<=0,"N.S",IF(AND(D59*E59>0,E59<0),-(E59-D59)/D59,(E59-D59)/D59)) -> N.S
A60: 13) DIVIDEND PAYABLE | C60: 0 | D60: 0 | E60: 0 | G60: =+E60-D60 -> 0 | H60: =+IF(D60*E60<=0,"N.S",IF(AND(D60*E60>0,E60<0),-(E60-D60)/D60,(E60-D60)/D60)) -> N.S
A61: 14) PROFIT (OR LOSS) PREVIOUS YEAR | C61: =+'input CEE'!G19/1000 -> 1039.039 | D61: =+'input CEE'!H19/1000 -> 1569.586 | E61: =+'input CEE'!I19/1000 -> 2531.513 | G61: =+E61-D61 -> 961.927 | H61: =+IF(D61*E61<=0,"N.S",IF(AND(D61*E61>0,E61<0),-(E61-D61)/D61,(E61-D61)/D61)) -> 0.61285396
A62: 15) PROFIT (OR LOSS) PRESENT YEAR | C62: =('input CEE'!G20+'input CEE'!G24)/1000 -> 558.47 | D62: =('input CEE'!H20+'input CEE'!H24)/1000 -> 1012.555 | E62: =('input CEE'!I20+'input CEE'!I24)/1000 -> 632.562 | G62: =+E62-D62 -> -379.993 | H62: =+IF(D62*E62<=0,"N.S",IF(AND(D62*E62>0,E62<0),-(E62-D62)/D62,(E62-D62)/D62)) -> -0.37528134
A63: D) NET WORTH (11+12+13+14+15+16) | C63: =+C49+C53+C60+C61+C62 -> 2691.583 | D63: =+D49+D53+D60+D61+D62 -> 3704.138 | E63: =+E49+E53+E60+E61+E62 -> 4336.698 | G63: =+E63-D63 -> 632.56 | H63: =+IF(D63*E63<=0,"N.S",IF(AND(D63*E63>0,E63<0),-(E63-D63)/D63,(E63-D63)/D63)) -> 0.17077118 | J63: =E63-(D63+E62) -> -0.002 | K63: =+J63 -> -0.002 | L63: =+'cash flow FGA'!B15 -> increase/(decrease) equity or reserve
A64: 18) LIQUIDITY | C64: =SUM(C65:C67) -> 3.417 | D64: =SUM(D65:D67) -> 1.035 | E64: =SUM(E65:E67) -> 0.678 | G64: =+E64-D64 -> -0.357 | H64: =+IF(D64*E64<=0,"N.S",IF(AND(D64*E64>0,E64<0),-(E64-D64)/D64,(E64-D64)/D64)) -> -0.34492754 | K64: =+G64+G68 -> -0.357 | L64: =+'cash flow FGA'!B23 -> increase/(decrease) financial receivables (or cash)
A65: Bank | C65: =+'input CEE'!B75/1000 -> 0 | D65: =+'input CEE'!C75/1000 -> 1.035 | E65: =+'input CEE'!D75/1000 -> 0 | G65: =+E65-D65 -> -1.035 | H65: =+IF(D65*E65<=0,"N.S",IF(AND(D65*E65>0,E65<0),-(E65-D65)/D65,(E65-D65)/D65)) -> N.S
A66: Cheques | C66: =+'input CEE'!B76/1000 -> 0 | D66: =+'input CEE'!C76/1000 -> 0 | E66: =+'input CEE'!D76/1000 -> 0 | G66: =+E66-D66 -> 0 | H66: =+IF(D66*E66<=0,"N.S",IF(AND(D66*E66>0,E66<0),-(E66-D66)/D66,(E66-D66)/D66)) -> N.S
A67: Cash | C67: =+'input CEE'!B77/1000 -> 3.417 | D67: =+'input CEE'!C77/1000 -> 0 | E67: =+'input CEE'!D77/1000 -> 0.678 | G67: =+E67-D67 -> 0.678 | H67: =+IF(D67*E67<=0,"N.S",IF(AND(D67*E67>0,E67<0),-(E67-D67)/D67,(E67-D67)/D67)) -> N.S
A68: 19) FINANCIAL RECEIVABLES | C68: =SUM(C69:C71) -> 0 | D68: =SUM(D69:D71) -> 0 | E68: =SUM(E69:E71) -> 0 | G68: =+E68-D68 -> 0 | H68: =+IF(D68*E68<=0,"N.S",IF(AND(D68*E68>0,E68<0),-(E68-D68)/D68,(E68-D68)/D68)) -> N.S
A69: Towards banks short, medium long term | C69: 0 | D69: 0 | E69: 0 | G69: =+E69-D69 -> 0 | H69: =+IF(D69*E69<=0,"N.S",IF(AND(D69*E69>0,E69<0),-(E69-D69)/D69,(E69-D69)/D69)) -> N.S
A70: Towards other short, medium long term | C70: ='input CEE'!B65/1000 -> 0 | D70: ='input CEE'!C65/1000 -> 0 | E70: ='input CEE'!D65/1000 -> 0 | G70: =+E70-D70 -> 0 | H70: =+IF(D70*E70<=0,"N.S",IF(AND(D70*E70>0,E70<0),-(E70-D70)/D70,(E70-D70)/D70)) -> N.S
A71: Intercompany financial receivables | C71: ='input CEE'!B52/1000 -> 0 | D71: ='input CEE'!C52/1000 -> 0 | E71: ='input CEE'!D52/1000 -> 0 | G71: =+E71-D71 -> 0 | H71: =+IF(D71*E71<=0,"N.S",IF(AND(D71*E71>0,E71<0),-(E71-D71)/D71,(E71-D71)/D71)) -> N.S
A72: 20) (FINANCIAL PAYABLES) | C72: =SUM(C73:C78) -> -41.257 | D72: =SUM(D73:D78) -> -45.235 | E72: =SUM(E73:E78) -> 0 | G72: =+E72-D72 -> 45.235 | H72: =+IF(D72*E72<=0,"N.S",IF(AND(D72*E72>0,E72<0),-(E72-D72)/D72,(E72-D72)/D72)) -> N.S
A73: Towards banks short term | C73: =-'input CEE'!G43/1000 -> -41.257 | D73: =-'input CEE'!H43/1000 -> -45.235 | E73: =-'input CEE'!I43/1000 -> 0 | G73: =+E73-D73 -> 45.235 | H73: =+IF(D73*E73<=0,"N.S",IF(AND(D73*E73>0,E73<0),-(E73-D73)/D73,(E73-D73)/D73)) -> N.S | K73: =+G73+G75+G78+G77 -> 45.235 | L73: =+'cash flow FGA'!B22 -> (increase)/decrease financial debts
A74: Towards banks long term (mortages) | C74: =-'input CEE'!G44/1000 -> 0 | D74: =-'input CEE'!H44/1000 -> 0 | E74: =-'input CEE'!I44/1000 -> 0 | G74: =+E74-D74 -> 0 | H74: =+IF(D74*E74<=0,"N.S",IF(AND(D74*E74>0,E74<0),-(E74-D74)/D74,(E74-D74)/D74)) -> N.S | K74: =+G74+G76 -> 0 | L74: =+'cash flow FGA'!B26 -> (increase)/decrease medium/long-term debts
A75: Other financial institutions short term | C75: =(-'input CEE'!G46-'input CEE'!G37-'input CEE'!G55)/1000 -> 0 | D75: =(-'input CEE'!H46-'input CEE'!H37-'input CEE'!H55)/1000 -> 0 | E75: =(-'input CEE'!I46-'input CEE'!I37-'input CEE'!I55)/1000 -> 0 | G75: =+E75-D75 -> 0 | H75: =+IF(D75*E75<=0,"N.S",IF(AND(D75*E75>0,E75<0),-(E75-D75)/D75,(E75-D75)/D75)) -> N.S
A76: Other financial institutions long term | C76: =(-'input CEE'!G47-'input CEE'!G38-'input CEE'!G56)/1000 -> 0 | D76: =(-'input CEE'!H47-'input CEE'!H38-'input CEE'!H56)/1000 -> 0 | E76: =(-'input CEE'!I47-'input CEE'!I38-'input CEE'!I56)/1000 -> 0 | G76: =+E76-D76 -> 0 | H76: =+IF(D76*E76<=0,"N.S",IF(AND(D76*E76>0,E76<0),-(E76-D76)/D76,(E76-D76)/D76)) -> N.S
A77: Shareholders funding | C77: =-('input CEE'!G40+'input CEE'!G41)/1000 -> 0 | D77: =-('input CEE'!H40+'input CEE'!H41)/1000 -> 0 | E77: =-('input CEE'!I40+'input CEE'!I41)/1000 -> 0 | G77: =+E77-D77 -> 0 | H77: =+IF(D77*E77<=0,"N.S",IF(AND(D77*E77>0,E77<0),-(E77-D77)/D77,(E77-D77)/D77)) -> N.S
A78: Intercompany financial payables | C78: =-('input CEE'!G60)/1000 -> 0 | D78: =-('input CEE'!H60)/1000 -> 0 | E78: =-('input CEE'!I60)/1000 -> 0 | G78: =+E78-D78 -> 0 | H78: =+IF(D78*E78<=0,"N.S",IF(AND(D78*E78>0,E78<0),-(E78-D78)/D78,(E78-D78)/D78)) -> N.S
A79: E) NET FINANCIAL POSITION (18+19+20) | C79: =+C64+C68+C72 -> -37.84 | D79: =+D64+D68+D72 -> -44.2 | E79: =+E64+E68+E72 -> 0.678 | G79: =+E79-D79 -> 44.878 | H79: =+IF(D79*E79<=0,"N.S",IF(AND(D79*E79>0,E79<0),-(E79-D79)/D79,(E79-D79)/D79)) -> N.S
A80: F) TOTAL NET LIABILITIES (D+E) | C80: =-C63+C79 -> -2729.423 | D80: =-D63+D79 -> -3748.338 | E80: =-E63+E79 -> -4336.02 | G80: =+E80-D80 -> -587.682 | H80: =+IF(D80*E80<=0,"N.S",IF(AND(D80*E80>0,E80<0),-(E80-D80)/D80,(E80-D80)/D80)) -> -0.15678469
A81: check | C81: =+C80+C48 -> 0 | D81: =+D80+D48 -> 0 | E81: =+E80+E48 -> 0
A83: PROFIT & LOSS
A84: A) TURNOVER | C84: ='input CEE'!B93/1000 -> 20727.579 | D84: ='input CEE'!C93/1000 -> 22640.669 | E84: ='input CEE'!D93/1000 -> 20375.419 | G84: =+E84-D84 -> -2265.25 | H84: =+IF(D84*E84<=0,"N.S",IF(AND(D84*E84>0,E84<0),-(E84-D84)/D84,(E84-D84)/D84)) -> -0.10005226
A85: Changes in inventories | C85: =('input CEE'!B94+'input CEE'!B95+'input CEE'!B96-'input CEE'!B114)/1000 -> 104.89 | D85: =('input CEE'!C94+'input CEE'!C95+'input CEE'!C96-'input CEE'!C114)/1000 -> 2834.256 | E85: =('input CEE'!D94+'input CEE'!D95+'input CEE'!D96-'input CEE'!D114)/1000 -> -2552.477 | G85: =+E85-D85 -> -5386.733 | H85: =+IF(D85*E85<=0,"N.S",IF(AND(D85*E85>0,E85<0),-(E85-D85)/D85,(E85-D85)/D85)) -> N.S
A86: (Cost of purchased goods) | C86: =-'input CEE'!B100/1000 -> -15717.452 | D86: =-'input CEE'!C100/1000 -> -19371.832 | E86: =-'input CEE'!D100/1000 -> -11824.508 | G86: =+E86-D86 -> 7547.324 | H86: =+IF(D86*E86<=0,"N.S",IF(AND(D86*E86>0,E86<0),-(E86-D86)/D86,(E86-D86)/D86)) -> 0.38960301
A87: Other operating income (and expenses) | C87: =('input CEE'!B97-'input CEE'!B117)/1000 -> 450.626 | D87: =('input CEE'!C97-'input CEE'!C117)/1000 -> 392.705 | E87: =('input CEE'!D97-'input CEE'!D117)/1000 -> 461.635 | G87: =+E87-D87 -> 68.93 | H87: =+IF(D87*E87<=0,"N.S",IF(AND(D87*E87>0,E87<0),-(E87-D87)/D87,(E87-D87)/D87)) -> 0.17552616
A88: B) GROSS PROFIT | C88: =SUM(C84:C87) -> 5565.643 | D88: =SUM(D84:D87) -> 6495.798 | E88: =SUM(E84:E87) -> 6460.069 | G88: =+E88-D88 -> -35.729 | H88: =+IF(D88*E88<=0,"N.S",IF(AND(D88*E88>0,E88<0),-(E88-D88)/D88,(E88-D88)/D88)) -> -0.005500325
A89: (General and Administrative Expenses) | C89: =-'input CEE'!B101/1000 -> -1073.498 | D89: =-'input CEE'!C101/1000 -> -1134.463 | E89: =-'input CEE'!D101/1000 -> -1169.802 | G89: =+E89-D89 -> -35.339 | H89: =+IF(D89*E89<=0,"N.S",IF(AND(D89*E89>0,E89<0),-(E89-D89)/D89,(E89-D89)/D89)) -> -0.031150421
A90: (Cost of Salaries and Wages) | C90: =-'input CEE'!B103/1000 -> -2346.318 | D90: =-'input CEE'!C103/1000 -> -2420.881 | E90: =-'input CEE'!D103/1000 -> -2747.028 | G90: =+E90-D90 -> -326.147 | H90: =+IF(D90*E90<=0,"N.S",IF(AND(D90*E90>0,E90<0),-(E90-D90)/D90,(E90-D90)/D90)) -> -0.13472244
A91: (Rent) | C91: =-'input CEE'!B102/1000 -> -540.135 | D91: =-'input CEE'!C102/1000 -> -555.118 | E91: =-'input CEE'!D102/1000 -> -635.922 | G91: =+E91-D91 -> -80.804 | H91: =+IF(D91*E91<=0,"N.S",IF(AND(D91*E91>0,E91<0),-(E91-D91)/D91,(E91-D91)/D91)) -> -0.14556184
A92: C) PROFIT BEFORE DEPRECIATION | C92: =SUM(C88:C91) -> 1605.692 | D92: =SUM(D88:D91) -> 2385.336 | E92: =SUM(E88:E91) -> 1907.317 | G92: =+E92-D92 -> -478.019 | H92: =+IF(D92*E92<=0,"N.S",IF(AND(D92*E92>0,E92<0),-(E92-D92)/D92,(E92-D92)/D92)) -> -0.20039902
A93: Provisions | C93: =-('input CEE'!B115+'input CEE'!B116)/1000 -> 0 | D93: =-('input CEE'!C115+'input CEE'!C116)/1000 -> -139.664 | E93: =-('input CEE'!D115+'input CEE'!D116)/1000 -> -182.505 | G93: =+E93-D93 -> -42.841 | H93: =+IF(D93*E93<=0,"N.S",IF(AND(D93*E93>0,E93<0),-(E93-D93)/D93,(E93-D93)/D93)) -> -0.30674333
A94: (Depreciation) | C94: =-'input CEE'!B111/1000 -> -748.679 | D94: =-'input CEE'!C111/1000 -> -681.909 | E94: =-'input CEE'!D111/1000 -> -762.648 | G94: =+E94-D94 -> -80.739 | H94: =+IF(D94*E94<=0,"N.S",IF(AND(D94*E94>0,E94<0),-(E94-D94)/D94,(E94-D94)/D94)) -> -0.11840143 | K94: =-E94-E95 -> 768.733 | L94: =+'cash flow FGA'!B5 -> depreciation
A95: (Amortization) | C95: =-'input CEE'!B110/1000 -> -7.471 | D95: =-'input CEE'!C110/1000 -> -7.176 | E95: =-'input CEE'!D110/1000 -> -6.085 | G95: =+E95-D95 -> 1.091 | H95: =+IF(D95*E95<=0,"N.S",IF(AND(D95*E95>0,E95<0),-(E95-D95)/D95,(E95-D95)/D95)) -> 0.15203456
A96: Recoveries | C96: =-('input CEE'!B113+'input CEE'!B112)/1000 -> -88.127 | D96: =-('input CEE'!C113+'input CEE'!C112)/1000 -> -56.128 | E96: =-('input CEE'!D113+'input CEE'!D112)/1000 -> -5.056 | G96: =+E96-D96 -> 51.072 | H96: =+IF(D96*E96<=0,"N.S",IF(AND(D96*E96>0,E96<0),-(E96-D96)/D96,(E96-D96)/D96)) -> 0.90992018
A97: D) OPERATING PROFIT | C97: =SUM(C92:C96) -> 761.415 | D97: =SUM(D92:D96) -> 1500.459 | E97: =SUM(E92:E96) -> 951.023 | G97: =+E97-D97 -> -549.436 | H97: =+IF(D97*E97<=0,"N.S",IF(AND(D97*E97>0,E97<0),-(E97-D97)/D97,(E97-D97)/D97)) -> -0.36617862
A98: Financial Income | C98: =('input CEE'!B122+'input CEE'!B128)/1000 -> 3.949 | D98: =('input CEE'!C122+'input CEE'!C128)/1000 -> 23.303 | E98: =('input CEE'!D122+'input CEE'!D128)/1000 -> 4.727 | G98: =+E98-D98 -> -18.576 | H98: =+IF(D98*E98<=0,"N.S",IF(AND(D98*E98>0,E98<0),-(E98-D98)/D98,(E98-D98)/D98)) -> -0.79715058
A99: (Financial Cost) | C99: =-('input CEE'!B133-'input CEE'!B139)/1000 -> -0.446 | D99: =-('input CEE'!C133-'input CEE'!C139)/1000 -> -9.737 | E99: =-('input CEE'!D133-'input CEE'!D139)/1000 -> -66.947 | G99: =+E99-D99 -> -57.21 | H99: =+IF(D99*E99<=0,"N.S",IF(AND(D99*E99>0,E99<0),-(E99-D99)/D99,(E99-D99)/D99)) -> -5.8755263
A100: Other non operating income (and expenses) | C100: =('input CEE'!B142-'input CEE'!B147)/1000 -> 0 | D100: =('input CEE'!C142-'input CEE'!C147)/1000 -> 0 | E100: =('input CEE'!D142-'input CEE'!D147)/1000 -> 0 | G100: =+E100-D100 -> 0 | H100: =+IF(D100*E100<=0,"N.S",IF(AND(D100*E100>0,E100<0),-(E100-D100)/D100,(E100-D100)/D100)) -> N.S
A101: F) PRE-TAX RESULT | C101: =C97+C98+C99+C100 -> 764.918 | D101: =D97+D98+D99+D100 -> 1514.025 | E101: =E97+E98+E99+E100 -> 888.803 | G101: =+E101-D101 -> -625.222 | H101: =+IF(D101*E101<=0,"N.S",IF(AND(D101*E101>0,E101<0),-(E101-D101)/D101,(E101-D101)/D101)) -> -0.41295355
A102: Taxes | C102: =-'input CEE'!B154/1000 -> -206.448 | D102: =-'input CEE'!C154/1000 -> -501.47 | E102: =-'input CEE'!D154/1000 -> -256.241 | G102: =+E102-D102 -> 245.229 | H102: =+IF(D102*E102<=0,"N.S",IF(AND(D102*E102>0,E102<0),-(E102-D102)/D102,(E102-D102)/D102)) -> 0.48902028
...

Sheet input CEE
A1: ATTIVO | B1: 2022 | C1: 2023 | D1: 2024 | F1: PASSIVO | G1: =+B1 -> 2022 | H1: =+C1 -> 2023 | I1: =+D1 -> 2024
A3: A) CREDITI VERSO SOCI PER VERSAMENTI | B3: =+B4+B5 -> 0 | C3: =+C4+C5 -> 0 | D3: =+D4+D5 -> 0 | F3: A) PATRIMONIO NETTO CONSOLIDATO | G3: =+G4+G22 -> 2691583 | H3: =+H4+H22 -> 3704138 | I3: =+I4+I22 -> 4336698
A4: 1) Parte da richiamare | F4: 1) PATRIMONIO NETTO | G4: =+G5+G6+G7+G8+G9+G10+G18+G19+G20+G21 -> 2691583 | H4: =+H5+H6+H7+H8+H9+H10+H18+H19+H20+H21 -> 3704138 | I4: =+I5+I6+I7+I8+I9+I10+I18+I19+I20+I21 -> 4336698
A5: 2) Parte richiamata | F5: I - Capitale | G5: 1000000 | H5: 1000000 | I5: 1000000
F6: II - Riserva di sovrapprezzo azioni | G6: 0 | H6: 0 | I6: 0
A7: B) IMMOBILIZZAZIONI | B7: =SUM(B8,B16,B22) -> 1761690 | C7: =SUM(C8,C16,C22) -> 2040654 | D7: =SUM(D8,D16,D22) -> 2611882 | F7: III - Riserva di rivalutazione | G7: 0 | H7: 0 | I7: 0
A8: I - IMMOBILIZZAZIONI IMMATERIALI | B8: =SUM(B9:B15) -> 12301 | C8: =SUM(C9:C15) -> 6565 | D8: =SUM(D9:D15) -> 480 | F8: IV - Riserva legale | G8: 94072 | H8: 121994 | I8: 172623
A9: 1) Costi d'impianto e di ampliamento | B9: 0 | C9: 0 | D9: 0 | F9: V - Riserva statutarie | G9: 0 | H9: 0 | I9: 0
A10: 2) Costi di sviluppo | B10: 0 | C10: 0 | D10: 0 | F10: VI - Altre riserve distintamente indicate | G10: =SUM(G11+G12+G13+G14+G15+G16+G17) -> 2 | H10: =SUM(H11+H12+H13+H14+H15+H16+H17) -> 3 | I10: =SUM(I11+I12+I13+I14+I15+I16+I17) -> 0
A11: 3) Diritto di brevetto industriale e di utilizzo delle opere d'ingegno | B11: 0 | C11: 0 | D11: 0 | F11: Riserva straordinaria o facoltativa
A12: 4) Concessioni, licenze, marchi e diritti simili | B12: 12301 | C12: 6565 | D12: 480 | F12: Versamenti in conto futuro aumento di capitale
A13: 5) Avviamento | B13: 0 | C13: 0 | D13: 0 | F13: Versamenti a coperture perdite
A14: 6) Immobilizzazioni in corso e acconti | B14: 0 | C14: 0 | D14: 0 | F14: Riserva avanzo di fusione
A15: 7) Altre | B15: 0 | C15: 0 | D15: 0 | F15: Riserva utili su cambi
A16: II - IMMOBILIZZAZIONI MATERIALI | B16: =SUM(B17:B21) -> 1708439 | C16: =SUM(C17:C21) -> 1993139 | D16: =SUM(D17:D21) -> 2551402 | F16: Differenza da arrotondamento all'unità di euro
A17: 1) Terreni e fabbricati | B17: 0 | C17: 0 | D17: 0 | F17: Varie altre riserve | G17: 2 | H17: 3 | I17: 0
A18: 2) Impianti e macchinari | B18: 0 | C18: 0 | D18: 0 | F18: VII - Riserva per operazioni di copertura dei flussi finanziari attesi
A19: 3) Attrezzature industriali e commerciali | B19: 15477 | C19: 19754 | D19: 7307 | F19: VIII - Utile (perdite) portate a nuovo | G19: 1039039 | H19: 1569586 | I19: 2531513
A20: 4) Altri beni | B20: 1692962 | C20: 1973385 | D20: 2544095 | F20: IX - Utile (perdita) dell'esercizio | G20: 558470 | H20: 1012555 | I20: 632562
A21: 5) Immobilizzazioni in corso e acconti | B21: 0 | C21: 0 | D21: 0 | F21: X - Riserva negativa per azioni proprie in portafoglio | G21: 0 | H21: 0 | I21: 0
A22: III - IMMOBILIZZAZIONI FINANZIARIE | B22: =SUM(B23+B29+B35+B36) -> 40950 | C22: =SUM(C23+C29+C35+C36) -> 40950 | D22: =SUM(D23+D29+D35+D36) -> 60000 | F22: 2) PATRIMONIO NETTO DI TERZI | G22: =+G23+G24 -> 0 | H22: =+H23+H24 -> 0 | I22: =+I23+I24 -> 0
A23: 1) Partecipazioni | B23: =SUM(B24:B28) -> 0 | C23: =SUM(C24:C28) -> 40950 | D23: =SUM(D24:D28) -> 0 | F23: I - Capitale e riserve di terzi
A24: a) imprese controllate | B24: 0 | C24: 0 | D24: 0 | F24: II - Utile (perdita) dell'esercizio di pertinenza di terzi
A25: b) imprese collegate | B25: 0 | C25: 0 | D25: 0
A26: c) imprese controllanti | B26: 0 | C26: 0 | D26: 0 | F26: B) FONDI PER RISCHI ED ONERI | G26: =+G27+G28+G29+G30 -> 5157 | H26: =+H27+H28+H29+H30 -> 144821 | I26: =+I27+I28+I29+I30 -> 187662
A27: d) imprese sottoposte al controllo delle controllanti | B27: 0 | C27: 0 | D27: 0 | F27: 1) Per trattamento di quiescenza ed obblighi simili | G27: 0 | H27: 0 | I27: 0
A28: d-bis) altre imprese | B28: 0 | C28: 40950 | D28: 0 | F28: 2) Per imposte, anche differite | G28: 0 | H28: 0 | I28: 0
A29: 2) Crediti | B29: =SUM(B30:B34) -> 40950 | C29: =SUM(C30:C34) -> 0 | D29: =SUM(D30:D34) -> 60000 | F29: 3) Per strumenti finanziari derivati passivi | G29: 0 | H29: 0 | I29: 0
A30: a) verso imprese controllate | B30: 0 | C30: 0 | D30: 0 | F30: 4) Altri fondi | G30: 5157 | H30: 144821 | I30: 187662
A31: b) verso imprese collegate | B31: 0 | C31: 0 | D31: 0
A32: c) verso controllanti | B32: 0 | C32: 0 | D32: 0 | F32: C) TRATTAMENTO DI FINE RAPPORTO | G32: =+G33 -> 0 | H32: =+H33 -> 0 | I32: =+I33 -> 0
A33: d) verso imprese sottoposte al controllo delle controllanti | B33: 0 | C33: 0 | D33: 0 | F33: 1) Per trattamento di fine rapporto | G33: 0 | H33: 0 | I33: 0
A34: d-bis) verso altri | B34: 40950 | C34: 0 | D34: 60000
A35: 3) Altri titoli | B35: 0 | C35: 0 | D35: 0 | F35: D) DEBITI | G35: =+G69+G66+G63+G60+G57+G54+G51+G48+G45+G42+G39+G36 -> 7491702 | H35: =+H69+H66+H63+H60+H57+H54+H51+H48+H45+H42+H39+H36 -> 10494034 | I35: =+I69+I66+I63+I60+I57+I54+I51+I48+I45+I42+I39+I36 -> 6457238
A36: 4) Strumenti finanziari derivati | B36: 0 | C36: 0 | D36: 0 | F36: 1-2) Obbligazioni (convertibili e non) | G36: =+G37+G38 -> 0 | H36: =+H37+H38 -> 0 | I36: =+I37+I38 -> 0
F37: Importi esigibili entro l'esercizio successivo | G37: 0 | H37: 0 | I37: 0
A38: C) ATTIVO CIRCOLANTE | B38: =B39+B45+B65+B74 -> 8470190 | C38: =C39+C45+C65+C74 -> 12321703 | D38: =D39+D45+D65+D74 -> 8363428 | F38: Importi esigibili oltre l'esercizio successivo | G38: 0 | H38: 0 | I38: 0
A39: I - RIMANENZE | B39: =SUM(B40:B44) -> 1943708 | C39: =SUM(C40:C44) -> 4786515 | D39: =SUM(D40:D44) -> 2217839 | F39: 3) Debiti verso soci per finanziamenti | G39: =+G40+G41 -> 0 | H39: =+H40+H41 -> 0 | I39: =+I40+I41 -> 0
A40: 1) Materie prime, sussidiarie e di consumo | B40: 1943708 | C40: 4786515 | D40: 2217839 | F40: Importi esigibili entro l'esercizio successivo | G40: 0 | H40: 0 | I40: 0
A41: 2) Prodotti in corso di lavorazione e semilavorati | F41: Importi esigibili oltre l'esercizio successivo | G41: 0 | H41: 0 | I41: 0
A42: 3) Lavori in corso su ordinazione | F42: 4) Debiti verso banche | G42: =+G43+G44 -> 41257 | H42: =+H43+H44 -> 45235 | I42: =+I43+I44 -> 0
A43: 4) Prodotti finiti e merci | F43: Importi esigibili entro l'esercizio successivo | G43: 41257 | H43: 45235 | I43: 0
A44: 5) Acconti | F44: Importi esigibili oltre l'esercizio successivo | G44: 0 | H44: 0 | I44: 0
A45: II - CREDITI | B45: =+B46+B49+B52+B56+B59+B62+B55 -> 6523065 | C45: =+C46+C49+C52+C56+C59+C62+C55 -> 7534153 | D45: =+D46+D49+D52+D56+D59+D62+D55 -> 6144911 | F45: 5) Debiti verso altri finanziatori | G45: =+G46+G47 -> 0 | H45: =+H46+H47 -> 0 | I45: =+I46+I47 -> 0
A46: 1) Verso clienti | B46: =+B47+B48 -> 4863670 | C46: =+C47+C48 -> 3807378 | D46: =+D47+D48 -> 3808801 | F46: Importi esigibili entro l'esercizio successivo | G46: 0 | H46: 0 | I46: 0
A47: Importi esigibili entro l'esercizio successivo | B47: 4863670 | C47: 3807378 | D47: 3808801 | F47: Importi esigibili oltre l'esercizio successivo | G47: 0 | H47: 0 | I47: 0
A48: Importi esigibili oltre l'esercizio successivo | B48: 0 | C48: 0 | D48: 0 | F48: 6) Acconti | G48: =+G49+G50 -> 1676350 | H48: =+H49+H50 -> 487318 | I48: =+I49+I50 -> 488547
A49: 2-3-4) Verso imprese controllate/collegate/controllanti (commerciali) | B49: =+B50+B51 -> 1327663 | C49: =+C50+C51 -> 2858485 | D49: =+D50+D51 -> 1996009 | F49: Importi esigibili entro l'esercizio successivo | G49: 1676350 | H49: 487318 | I49: 488547
A50: Importi esigibili entro l'esercizio successivo | B50: 1327663 | C50: 2858485 | D50: 1996009 | F50: Importi esigibili oltre l'esercizio successivo | G50: 0 | H50: 0 | I50: 0
A51: Importi esigibili oltre l'esercizio successivo | B51: 0 | C51: 0 | D51: 0 | F51: 7) Debiti verso fornitori | G51: =+G52+G53 -> 947195 | H51: =+H52+H53 -> 1032244 | I51: =+I52+I53 -> 972098
A52: 2-3-4) Verso imprese controllate/collegate/controllanti (finanziari) | B52: =+B53+B54 -> 0 | C52: =+C53+C54 -> 0 | D52: =+D53+D54 -> 0 | F52: Importi esigibili entro l'esercizio successivo | G52: 947195 | H52: 1032244 | I52: 972098
A53: Importi esigibili entro l'esercizio successivo | B53: 0 | C53: 0 | D53: 0 | F53: Importi esigibili oltre l'esercizio successivo | G53: 0 | H53: 0 | I53: 0
A54: Importi esigibili oltre l'esercizio successivo | F54: 8) Debiti rappresentati da titoli di credito | G54: =+G55+G56 -> 0 | H54: =+H55+H56 -> 0 | I54: =+I55+I56 -> 0
A55: 5) Verso imprese sottoposte al controllo delle controllanti | F55: Importi esigibili entro l'esercizio successivo | G55: 0 | H55: 0 | I55: 0
A56: 5-bis) Crediti tributari | B56: =+B57+B58 -> 78517 | C56: =+C57+C58 -> 579544 | D56: =+D57+D58 -> 10257 | F56: Importi esigibili oltre l'esercizio successivo | G56: 0 | H56: 0 | I56: 0
A57: Importi esigibili entro l'esercizio successivo | B57: 78517 | C57: 579544 | D57: 10257 | F57: 9-10-11- 11-bis*) Debiti verso imprese controllate/collegate/controllanti (commerciali) | G57: =+G58+G59 -> 4193285 | H57: =+H58+H59 -> 8306699 | I57: =+I58+I59 -> 4233159
A58: Importi esigibili oltre l'esercizio successivo | B58: 0 | C58: 0 | D58: 0 | F58: Importi esigibili entro l'esercizio successivo | G58: 4193285 | H58: 8306699 | I58: 4233159
A59: 5-ter) Imposte anticipate | B59: =+B60+B61 -> 245670 | C59: =+C60+C61 -> 276152 | D59: =+D60+D61 -> 296791 | F59: Importi esigibili oltre l'esercizio successivo
A60: Importi esigibili entro l'esercizio successivo | B60: 245670 | C60: 276152 | D60: 296791 | F60: 9-10-11-11-bis*) Debiti verso imprese controllate/collegate/controllanti (finanziari) | G60: =+G61+G62 -> 0 | H60: =+H61+H62 -> 0 | I60: =+I61+I62 -> 0
A61: Importi esigibili oltre l'esercizio successivo | B61: 0 | C61: 0 | D61: 0 | F61: Importi esigibili entro l'esercizio successivo | G61: 0 | H61: 0 | I61: 0
A62: 5-quater) Verso altri | B62: =+B63+B64 -> 7545 | C62: =+C63+C64 -> 12594 | D62: =+D63+D64 -> 33053 | F62: Importi esigibili oltre l'esercizio successivo | G62: 0 | H62: 0 | I62: 0
A63: Importi esigibili entro l'esercizio successivo | B63: 7545 | C63: 12594 | D63: 33053 | F63: 12) Debiti tributari | G63: =+G64+G65 -> 91186 | H63: =+H64+H65 -> 94968 | I63: =+I64+I65 -> 263495
A64: Importi esigibili oltre l'esercizio successivo | B64: 0 | C64: 0 | D64: 0 | F64: Importi esigibili entro l'esercizio successivo | G64: 91186 | H64: 94968 | I64: 263495
A65: III - ATTIVITA' FINANZIARIE CHE NON COSTIT. IMMOBILIZZAZIONI | B65: =SUM(B66:B73) -> 0 | C65: =SUM(C66:C73) -> 0 | D65: =SUM(D66:D73) -> 0 | F65: Importi esigibili oltre l'esercizio successivo | G65: 0 | H65: 0 | I65: 0
A66: 1) Partecipazioni in imprese controllate | B66: 0 | C66: 0 | D66: 0 | F66: 13) Debiti verso Istituti di prev. e sicurezza sociale | G66: =+G67+G68 -> 128320 | H66: =+H67+H68 -> 134317 | I66: =+I67+I68 -> 141088
A67: 2) Partecipazioni in imprese collegate | B67: 0 | C67: 0 | D67: 0 | F67: Importi esigibili entro l'esercizio successivo | G67: 128320 | H67: 134317 | I67: 141088
A68: 3) Partecipazioni in imprese controllanti | B68: 0 | C68: 0 | D68: 0 | F68: Importi esigibili oltre l'esercizio successivo | G68: 0 | H68: 0 | I68: 0 | K68: 11-bis* | L68: Debiti verso imprese sottoposte al controllo delle controllanti
A69: 3-bis) Partecipazioni in imprese sottoposte al controllo delle controllanti | B69: 0 | C69: 0 | D69: 0 | F69: 14) Altri debiti | G69: =+G70+G71 -> 414109 | H69: =+H70+H71 -> 393253 | I69: =+I70+I71 -> 358851
A70: 4) Altre partecipazioni | B70: 0 | C70: 0 | D70: 0 | F70: Importi esigibili entro l'esercizio successivo | G70: 414109 | H70: 393253 | I70: 358851
A71: 5) Strumenti finanziari derivati attivi | B71: 0 | C71: 0 | D71: 0 | F71: Importi esigibili oltre l'esercizio successivo | G71: 0 | H71: 0 | I71: 0
A72: 6) Altri titoli | B72: 0 | C72: 0 | D72: 0
A73: 7) Altre | B73: 0 | C73: 0 | D73: 0
A74: IV - DISPONIBILITA' LIQUIDE | B74: =SUM(B75:B77) -> 3417 | C74: =SUM(C75:C77) -> 1035 | D74: =SUM(D75:D77) -> 678 | F74: E) RATEI E RISCONTI | G74: =+G75+G76 -> 71459 | H74: =+H75+H76 -> 42554 | I74: =+I75+I76 -> 20848
A75: 1) Depositi bancari e postali | B75: 0 | C75: 1035 | D75: 0 | F75: 1) Ratei e risconti | G75: 71459 | H75: 42554 | I75: 20848
A76: 2) Assegni | B76: 0 | C76: 0 | D76: 0 | F76: 2) Aggio su prestiti
A77: 3) Denaro e valori in cassa | B77: 3417 | C77: 0 | D77: 678
F78: TOTALE (A + B + C + D + E) | G78: =G3+G26+G32+G74+G35 -> 10259901 | H78: =H3+H26+H32+H74+H35 -> 14385547 | I78: =I3+I26+I32+I74+I35 -> 11002446
A79: D) RATEI E RISCONTI | B79: =SUM(B80:B82) -> 28021 | C79: =SUM(C80:C82) -> 23190 | D79: =SUM(D80:D82) -> 27136
A80: 1) Ratei e risconti | B80: 28021 | C80: 23190 | D80: 27136 | F80: chk | G80: =+G78-B84 -> 0 | H80: =+H78-C84 -> 0 | I80: =+I78-D84 -> 0
A81: 2) Costi anticipati
A82: 3) Disaggio su prestiti
A84: TOTALE (A + B + C + D) | B84: =B3+B7+B38+B79 -> 10259901 | C84: =C3+C7+C38+C79 -> 14385547 | D84: =D3+D7+D38+D79 -> 11002446
A90: CONTO ECONOMICO | B90: =+B1 -> 2022 | C90: =+C1 -> 2023 | D90: =+D1 -> 2024
A92: A) VALORE DELLA PRODUZIONE | B92: =+B93+B94+B95+B96+B97 -> 21197167 | C92: =+C93+C94+C95+C96+C97 -> 23058458 | D92: =+D93+D94+D95+D96+D97 -> 20867544
A93: 1) Ricavi delle vendite e delle prestazioni | B93: 20727579 | C93: 22640669 | D93: 20375419
A94: 2) Variazioni delle rimanenze di prodotti in corso di lavorazione, semilavorati e finiti | B94: 0 | C94: 0 | D94: 0
A95: 3) Variazioni dei lavori in corso su ordinazione
A96: 4) Incrementi di immobilizzazioni per lavori interni | B96: 0 | C96: 0 | D96: 0
A97: 5) Altri ricavi e proventi | B97: 469588 | C97: 417789 | D97: 492125
A99: B) COSTI DELLA PRODUZIONE | B99: =+B100+B101+B102+B103+B109+B114+B115+B116+B117 -> 20435752 | C99: =+C100+C101+C102+C103+C109+C114+C115+C116+C117 -> 21557999 | D99: =+D100+D101+D102+D103+D109+D114+D115+D116+D117 -> 19916521
A100: 6) Per materie prime,sussidiarie, di consumo e di merci | B100: 15717452 | C100: 19371832 | D100: 11824508
A101: 7) Per servizi | B101: 1073498 | C101: 1134463 | D101: 1169802
A102: 8) Per godimento beni di terzi | B102: 540135 | C102: 555118 | D102: 635922
A103: 9) Per il personale | B103: =+B104+B105+B106+B107+B108 -> 2346318 | C103: =+C104+C105+C106+C107+C108 -> 2420881 | D103: =+D104+D105+D106+D107+D108 -> 2747028
A104: a) Salari e stipendi | B104: 2346318 | C104: 2420881 | D104: 2747028
A105: b) Oneri sociali
A106: c) Trattamento di fine rapporto
A107: d) Trattamento di quiescenza e simili
A108: e) Altri costi
A109: 10) Ammortamenti e svalutazioni | B109: =+B110+B111+B112+B113 -> 844277 | C109: =+C110+C111+C112+C113 -> 745213 | D109: =+D110+D111+D112+D113 -> 773789
...
